streamson_python-4.0.0.dist-info/METADATA
streamson_python-4.0.0.dist-info/WHEEL
streamson_python-4.0.0.dist-info/entry_points.txt
streamson/__init__.py
streamson/convert.py
streamson/trigger.py
streamson/filter.py
streamson/handler.py
streamson/all.py
streamson/output.py
streamson/__pycache__/__init__.cpython-38.pyc
streamson/__pycache__/matcher.cpython-38.pyc
streamson/__pycache__/__init__.cpython-39.pyc
streamson/__pycache__/extract.cpython-38.pyc
streamson/__pycache__/convert.cpython-39.pyc
streamson/__pycache__/handler.cpython-39.pyc
streamson/__pycache__/filter.cpython-39.pyc
streamson/__pycache__/all.cpython-39.pyc
streamson/__pycache__/extract.cpython-39.pyc
streamson/__pycache__/trigger.cpython-38.pyc
streamson/__pycache__/convert.cpython-38.pyc
streamson/__pycache__/trigger.cpython-39.pyc
streamson/__pycache__/__init__.cpython-37.pyc
streamson/__pycache__/matcher.cpython-39.pyc
streamson/extract.py
streamson/__main__.py
streamson/matcher.py
streamson/streamson.cpython-39-x86_64-linux-gnu.so
streamson_python-4.0.0.dist-info/RECORD
