Metadata-Version: 2.1
Name: streamson-python
Version: 4.0.0
Summary: Python wrappers around streamson
Keywords: json python splitter
Author: Stepan Henek
License: MIT
